claudius/__init__.py
claudius/calc_field.py
claudius/coords.py
claudius/core.py
claudius/far_field.py
claudius/normL2.py
claudius/solve_prob.py
claudius/utils.py
claudius/Helmholtz_2d/__init__.py
claudius/Helmholtz_2d/base_fun.py
claudius/Helmholtz_2d/calc_field.py
claudius/Helmholtz_2d/plane_wave.py
claudius/Helmholtz_2d/prob_cst.py
claudius/Helmholtz_2d/utils.py
claudius/Helmholtz_3d/__init__.py
claudius/Helmholtz_3d/base_fun.py
claudius/Helmholtz_3d/calc_field.py
claudius/Helmholtz_3d/plane_wave.py
claudius/Helmholtz_3d/prob_cst.py
claudius/Helmholtz_3d/utils.py
claudius/Maxwell_3d/__init__.py
claudius/Maxwell_3d/base_fun.py
claudius/Maxwell_3d/calc_field.py
claudius/Maxwell_3d/plane_wave.py
claudius/Maxwell_3d/prob_cst.py
claudius/Maxwell_3d/utils.py
claudius/plot/__init__.py
claudius/plot/anim_field.py
claudius/plot/plot.py
claudius/plot/plot_far_field.py
claudius/plot/plot_field.py
claudius-1.1.1.dist-info/LICENSE
claudius-1.1.1.dist-info/WHEEL
claudius-1.1.1.dist-info/METADATA
claudius-1.1.1.dist-info/RECORD
