Metadata-Version: 2.1
Name: claudius
Version: 1.1.1
Summary: Analytic computations for scattering
Home-page: https://github.com/zmoitier/claudius
License: UNKNOWN
Author: Zoïs Moitier
Author-email: z.moitier@gmail.com
Requires-Python: >=3.7
Classifier: Intended Audience :: Science/Research
Classifier: License :: OSI Approved :: MIT License
Classifier: Programming Language :: Python :: 3 :: Only
Classifier: Topic :: Scientific/Engineering :: Mathematics
Classifier: Topic :: Software Development :: Libraries :: Python Modules
Requires-Dist: numba>=0.51.2
Requires-Dist: numpy>=1.19.4
Requires-Dist: scipy>=1.5.4
Requires-Dist: black==20.8b1 ; extra == "dev"
Requires-Dist: isort==5.6.4 ; extra == "dev"
Requires-Dist: pytest==6.1.2 ; extra == "dev"
Requires-Dist: pytest-cov==2.10.1 ; extra == "dev"
Requires-Dist: matplotlib>=3.3.3 ; extra == "plot"
Provides-Extra: dev
Provides-Extra: plot
